maphis/LICENSE
maphis/__init__.py
maphis/__main__.py
maphis/app.py
maphis/color_tolerance_dialog.py
maphis/custom_graphics_view.py
maphis/filter_widget.py
maphis/image_list_delegate.py
maphis/image_list_model.py
maphis/image_viewer.py
maphis/import_dialog.py
maphis/import_utils.py
maphis/photo_filter.py
maphis/plugin_creation.py
maphis/plugin_manager_.py
maphis/reflections_label_hierarchy.json
maphis/regions_label_hierarchy.json
maphis/resources.py
maphis/resources.qrc
maphis/tag_filter_widget.py
maphis/tags_widget.py
maphis/thumbnail_gui.py
maphis/thumbnail_storage.py
maphis/ui_about.py
maphis/ui_color_tolerance_dialog.py
maphis/ui_image_viewer.py
maphis/ui_image_viewer.ui
maphis/ui_import_dialog.py
maphis/ui_maphis.py
maphis/ui_plugins_widget.py
maphis/ui_progress_dialog.py
maphis/ui_thumbnail_gui.py
maphis/bin/__init__.py
maphis/common/__init__.py
maphis/common/action.py
maphis/common/blocking_operation.py
maphis/common/choice.py
maphis/common/choice_popup_panel.py
maphis/common/common.py
maphis/common/computations_scheduler.py
maphis/common/download.py
maphis/common/edit_command_executor.py
maphis/common/icon_storage.py
maphis/common/image_operation_binding.py
maphis/common/label_change.py
maphis/common/label_hierarchy.py
maphis/common/label_image.py
maphis/common/label_tree_model.py
maphis/common/label_tree_view.py
maphis/common/local_photo.py
maphis/common/local_storage.py
maphis/common/message_widget.py
maphis/common/new_plugin.py
maphis/common/param_widget.py
maphis/common/photo.py
maphis/common/plugin.py
maphis/common/plugin_utils.py
maphis/common/popup_widget.py
maphis/common/regions_cache.py
maphis/common/scale_setting_widget.py
maphis/common/state.py
maphis/common/storage.py
maphis/common/tool.py
maphis/common/undo_manager.py
maphis/common/units.py
maphis/common/user_param.py
maphis/common/user_params.py
maphis/common/utils.py
maphis/label_editor/__init__.py
maphis/label_editor/computation_widget.py
maphis/label_editor/label_editor.py
maphis-1.0.9.dist-info/LICENSE
maphis-1.0.9.dist-info/METADATA
maphis-1.0.9.dist-info/WHEEL
maphis-1.0.9.dist-info/top_level.txt
maphis-1.0.9.dist-info/RECORD
