Metadata-Version: 2.1
Name: maphis
Version: 1.0.9
Summary: Hierarchical segmentation and extraction of various measurements from photos of (not only) arthropods.
Author-email: Petr Matula <pem@fi.muni.cz>, Radoslav Mráz <rmraz@mail.muni.cz>, Matěj Pekár <matej.pekar120@gmail.com>, Stanislav Pekár <pekar@sci.muni.cz>, Karel Štěpka <chuckie@mail.muni.cz>
Maintainer-email: Radoslav Mráz <rmraz@mail.muni.cz>
License: GNU GENERAL PUBLIC LICENSE
Project-URL: homepage, https://maphis.fi.muni.cz
Project-URL: repository, https://gitlab.fi.muni.cz/cbia/maphis
Keywords: hierarchical segmentation,segmentation,measurements,arthropods
Classifier: Development Status :: 5 - Production/Stable
Classifier: Environment :: Win32 (MS Windows)
Classifier: Environment :: X11 Applications :: Qt
Classifier: Intended Audience :: Science/Research
Classifier: License :: OSI Approved :: GNU General Public License v3 (GPLv3)
Classifier: Operating System :: MacOS
Classifier: Operating System :: Microsoft :: Windows
Classifier: Operating System :: Microsoft :: Windows :: Windows 10
Classifier: Operating System :: Microsoft :: Windows :: Windows 11
Classifier: Operating System :: POSIX :: Linux
Classifier: Programming Language :: Python :: 3 :: Only
Classifier: Programming Language :: Python :: 3
Classifier: Programming Language :: Python :: 3.8
Classifier: Programming Language :: Python :: 3.9
Classifier: Programming Language :: Python :: 3.10
Classifier: Programming Language :: Python :: 3.11
Classifier: Topic :: Scientific/Engineering
Classifier: Topic :: Scientific/Engineering :: Image Processing
Requires-Python: >=3.8
License-File: LICENSE
Requires-Dist: platformdirs
Requires-Dist: numpy
Requires-Dist: scikit-image
Requires-Dist: PySide6
Requires-Dist: opencv-python
Requires-Dist: Pillow
Requires-Dist: imagecodecs
Requires-Dist: numba
Requires-Dist: openpyxl
Requires-Dist: scikit-learn
Requires-Dist: scipy
Requires-Dist: pytesseract
Requires-Dist: mouse
Requires-Dist: torch
Requires-Dist: arthseg
Requires-Dist: pyparsing
Requires-Dist: requests
Requires-Dist: pint
